[
{"BlkBegDaq":3435973836,"MdlRunCnt":44839,"BlkNotTrc":"","MdlAirScl":175,"MdlGraScl":145,"MdlDisErr":5,"MdlInjOut":25,"MdlDruOut":65,"MdlAirOut":75,"BlkNt2Trc":"","BlkEndDaq":3722304989},
{"BlkBegDaq":3435973836,"MdlRunCnt":44840,"BlkNotTrc":"","MdlAirScl":175,"MdlGraScl":145,"MdlDisErr":5,"MdlInjOut":25,"MdlDruOut":65,"MdlAirOut":75,"BlkNt2Trc":"","BlkEndDaq":3722304989},
{"BlkBegDaq":3435973836,"MdlRunCnt":44841,"BlkNotTrc":"","MdlAirScl":175,"MdlGraScl":145,"MdlDisErr":5,"MdlInjOut":25,"MdlDruOut":65,"MdlAirOut":75,"BlkNt2Trc":"","BlkEndDaq":3722304989},
{"BlkBegDaq":3435973836,"MdlRunCnt":44842,"BlkNotTrc":"","MdlAirScl":175,"MdlGraScl":145,"MdlDisErr":5,"MdlInjOut":25,"MdlDruOut":65,"MdlAirOut":75,"BlkNt2Trc":"","BlkEndDaq":3722304989},
{"BlkBegDaq":3435973836,"MdlRunCnt":44843,"BlkNotTrc":"","MdlAirScl":175,"MdlGraScl":145,"MdlDisErr":5,"MdlInjOut":25,"MdlDruOut":65,"MdlAirOut":75,"BlkNt2Trc":"","BlkEndDaq":3722304989},
{"BlkBegDaq":3435973836,"MdlRunCnt":44844,"BlkNotTrc":"","MdlAirScl":175,"MdlGraScl":145,"MdlDisErr":5,"MdlInjOut":25,"MdlDruOut":65,"MdlAirOut":75,"BlkNt2Trc":"","BlkEndDaq":3722304989},
{"BlkBegDaq":3435973836,"MdlRunCnt":44845,"BlkNotTrc":"","MdlAirScl":175,"MdlGraScl":145,"MdlDisErr":5,"MdlInjOut":25,"MdlDruOut":65,"MdlAirOut":75,"BlkNt2Trc":"","BlkEndDaq":3722304989},
{"BlkBegDaq":3435973836,"MdlRunCnt":44846,"BlkNotTrc":"","MdlAirScl":175,"MdlGraScl":145,"MdlDisErr":5,"MdlInjOut":25,"MdlDruOut":65,"MdlAirOut":75,"BlkNt2Trc":"","BlkEndDaq":3722304989},
{"BlkBegDaq":3435973836,"MdlRunCnt":44847,"BlkNotTrc":"","MdlAirScl":175,"MdlGraScl":145,"MdlDisErr":5,"MdlInjOut":25,"MdlDruOut":65,"MdlAirOut":75,"BlkNt2Trc":"","BlkEndDaq":3722304989},
{"BlkBegDaq":3435973836,"MdlRunCnt":44848,"BlkNotTrc":"","MdlAirScl":175,"MdlGraScl":145,"MdlDisErr":5,"MdlInjOut":25,"MdlDruOut":65,"MdlAirOut":75,"BlkNt2Trc":"","BlkEndDaq":3722304989},
{"BlkBegDaq":3435973836,"MdlRunCnt":44849,"BlkNotTrc":"","MdlAirScl":175,"MdlGraScl":145,"MdlDisErr":5,"MdlInjOut":25,"MdlDruOut":65,"MdlAirOut":75,"BlkNt2Trc":"","BlkEndDaq":3722304989},
{"BlkBegDaq":3435973836,"MdlRunCnt":44850,"BlkNotTrc":"","MdlAirScl":175,"MdlGraScl":145,"MdlDisErr":5,"MdlInjOut":25,"MdlDruOut":65,"MdlAirOut":75,"BlkNt2Trc":"","BlkEndDaq":3722304989},
{"BlkBegDaq":3435973836,"MdlRunCnt":44851,"BlkNotTrc":"","MdlAirScl":175,"MdlGraScl":145,"MdlDisErr":5,"MdlInjOut":25,"MdlDruOut":65,"MdlAirOut":75,"BlkNt2Trc":"","BlkEndDaq":3722304989},
{"BlkBegDaq":3435973836,"MdlRunCnt":44852,"BlkNotTrc":"","MdlAirScl":175,"MdlGraScl":145,"MdlDisErr":5,"MdlInjOut":25,"MdlDruOut":65,"MdlAirOut":75,"BlkNt2Trc":"","BlkEndDaq":3722304989}
]